LICENSE
MANIFEST.in
README.md
license_info.py
setup.py
license_info.egg-info/PKG-INFO
license_info.egg-info/SOURCES.txt
license_info.egg-info/dependency_links.txt
license_info.egg-info/entry_points.txt
license_info.egg-info/requires.txt
license_info.egg-info/top_level.txt