Metadata-Version: 1.1
Name: license-info
Version: 0.8.5
Summary: Show list of installed python packages with version and license info
Home-page: https://github.com/odiroot/license-info
Author: Michal Odnous
Author-email: odi.root@gmail.com
License: BSD
Platform: UNKNOWN
Classifier: Development Status :: 3 - Alpha
Classifier: Environment :: Console
Classifier: Intended Audience :: Developers
Classifier: License :: OSI Approved :: BSD License
Classifier: Operating System :: MacOS :: MacOS X
Classifier: Operating System :: POSIX
Classifier: Programming Language :: Python
Classifier: Topic :: Software Development
Classifier: Topic :: Utilities
